window_capture_streaming/LICENSE
window_capture_streaming/README.MD
window_capture_streaming/__init__.py
window_capture_streaming/requirements.txt
window_capture_streaming/thirdparty.json
window_capture_streaming-0.14.dist-info/LICENSE.rst
window_capture_streaming-0.14.dist-info/METADATA
window_capture_streaming-0.14.dist-info/WHEEL
window_capture_streaming-0.14.dist-info/top_level.txt
window_capture_streaming-0.14.dist-info/RECORD
